open_source_template/__init__.py
open_source_template/main.py
open_source_template-1.2.2.dist-info/METADATA
open_source_template-1.2.2.dist-info/WHEEL
open_source_template-1.2.2.dist-info/licenses/AUTHORS
open_source_template-1.2.2.dist-info/licenses/LICENSE
open_source_template-1.2.2.dist-info/RECORD
