Metadata-Version: 2.4
Name: open-source-template
Version: 1.2.2
Summary: A demo for the OSS template at MeteoSwiss.
License: BSD-3-Clause
License-File: AUTHORS
License-File: LICENSE
Author: Michele Cattaneo
Author-email: michele.cattaneo@meteoswiss.ch
Requires-Python: >=3.10,<3.13
Classifier: License :: OSI Approved :: BSD License
Classifier: Programming Language :: Python :: 3
Classifier: Programming Language :: Python :: 3.10
Classifier: Programming Language :: Python :: 3.11
Classifier: Programming Language :: Python :: 3.12
